kk_flow/__init__.py
kk_flow/nn/__init__.py
kk_flow/nn/core.py
kk_flow/utils/__init__.py
kk_flow/utils/utilities.py
kk_flow-0.0.2.dist-info/LICENSE
kk_flow-0.0.2.dist-info/METADATA
kk_flow-0.0.2.dist-info/WHEEL
kk_flow-0.0.2.dist-info/top_level.txt
kk_flow-0.0.2.dist-info/RECORD
