Metadata-Version: 2.1
Name: kk-flow
Version: 0.0.2
Summary: This is a mini but function completed neural networks framework
Home-page: UNKNOWN
Author: Krasjet_Yu
Author-email: krasjet.ziping@gmail.com
License: UNKNOWN
Platform: UNKNOWN
Classifier: Programming Language :: Python :: 3
Classifier: License :: OSI Approved :: MIT License
Classifier: Operating System :: OS Independent
Requires-Python: >=3.6
